LICENSE
README.md
setup.py
picproba/__init__.py
picproba/_helper.py
picproba/_test.py
picproba/errors.py
picproba/nb_typ.py
picproba/proba.py
picproba/proba_map.py
picproba/types.py
picproba/warnings.py
picproba.egg-info/PKG-INFO
picproba.egg-info/SOURCES.txt
picproba.egg-info/dependency_links.txt
picproba.egg-info/requires.txt
picproba.egg-info/top_level.txt
picproba/discrete/__init__.py
picproba/discrete/discrete.py
picproba/discrete/discrete_map.py
picproba/exponential_family/__init__.py
picproba/exponential_family/beta.py
picproba/exponential_family/exponential.py
picproba/exponential_family/exponential_family.py
picproba/exponential_family/gamma.py
picproba/exponential_family/pareto.py
picproba/exponential_family/pre_exponential_family.py
picproba/gauss/__init__.py
picproba/gauss/fixed_cov_gaussian_map.py
picproba/gauss/gauss_hyperball.py
picproba/gauss/gauss_hypercube.py
picproba/gauss/BlockGauss/__init__.py
picproba/gauss/BlockGauss/block_diag.py
picproba/gauss/BlockGauss/block_diag_map.py
picproba/gauss/BlockGauss/helper.py
picproba/gauss/BlockGauss/nb_helper/__init__.py
picproba/gauss/BlockGauss/nb_helper/aot.py
picproba/gauss/Gauss/__init__.py
picproba/gauss/Gauss/gaussian.py
picproba/gauss/Gauss/gaussian_map.py
picproba/gauss/Gauss/nb_helper/__init__.py
picproba/gauss/Gauss/nb_helper/_aot_comp.py
picproba/gauss/TGauss/__init__.py
picproba/gauss/TGauss/t_gaussian.py
picproba/gauss/TGauss/t_gaussian_map.py