Metadata-Version: 2.1
Name: picproba
Version: 0.0.1
Summary: Probability distribution management
Author: Antoine Picard-Weibel
Author-email: apicard.w@gmail.com
Classifier: Programming Language :: Python :: 3
Classifier: License :: OSI Approved :: MIT License
Classifier: Operating System :: OS Independent
Requires-Python: >=3.9
License-File: LICENSE
Requires-Dist: apicutils>=0.0.2
Requires-Dist: pandas
Requires-Dist: scipy>=1.7.0
Requires-Dist: numpy<=1.26
Requires-Dist: numba==0.58.1
